[
    {
        "id": 1,
        "title": "கிறிஸ்மஸ் கொண்டாட்டம்",
        "date": "2026-12-25",
        "description": "எங்கள் தேவாலயத்தில் கிறிஸ்துமஸ் மகிழ்ச்சியையும் இயேசுவின் பிறப்பையும் கொண்டாட எங்களுடன் இணையுங்கள். சிறப்பு ஆராதனை, கேரல் மற்றும் சமூக விருந்து நடைபெறும்.",
        "image": "https://images.unsplash.com/photo-1543589077-47d81606c1bf?q=80&w=600&auto=format&fit=crop"
    },
    {
        "id": 2,
        "title": "புத்தாண்டு ஆராதனை",
        "date": "2027-01-01",
        "description": "நள்ளிரவு ஆராதனை மற்றும் ஜெபத்துடன் புத்தாண்டில் அடியெடுத்து வையுங்கள். நாம் கடந்த காலத்தைத் திரும்பிப் பார்த்து, எதிர்காலத்திற்காக கடவுளிடம் ஒப்படைப்போம்.",
        "image": "https://images.unsplash.com/photo-1467810563316-b5476525c0f9?q=80&w=600&auto=format&fit=crop"
    },
    {
        "id": 3,
        "title": "இளைஞர் முகாம் 2026",
        "date": "2026-06-15",
        "description": "இளைஞர்களுக்கான மாற்றத்தை ஏற்படுத்தும் வார இறுதி முகாம். வழிபாடு, பட்டறைகள் மற்றும் வேடிக்கையான செயல்பாடுகளில் கலந்து கொள்ளுங்கள்.",
        "image": "https://images.unsplash.com/photo-1523580494863-6f3031224c94?q=80&w=600&auto=format&fit=crop"
    }
]